allennlp_light/__init__.py
allennlp_light/py.typed
allennlp_light/version.py
allennlp_light/modules/__init__.py
allennlp_light/modules/augmented_lstm.py
allennlp_light/modules/bimpm_matching.py
allennlp_light/modules/encoder_base.py
allennlp_light/modules/feedforward.py
allennlp_light/modules/gated_sum.py
allennlp_light/modules/highway.py
allennlp_light/modules/input_variational_dropout.py
allennlp_light/modules/layer_norm.py
allennlp_light/modules/lstm_cell_with_projection.py
allennlp_light/modules/masked_layer_norm.py
allennlp_light/modules/maxout.py
allennlp_light/modules/residual_with_layer_dropout.py
allennlp_light/modules/sampled_softmax_loss.py
allennlp_light/modules/scalar_mix.py
allennlp_light/modules/softmax_loss.py
allennlp_light/modules/stacked_alternating_lstm.py
allennlp_light/modules/stacked_bidirectional_lstm.py
allennlp_light/modules/time_distributed.py
allennlp_light/modules/util.py
allennlp_light/modules/attention/__init__.py
allennlp_light/modules/attention/additive_attention.py
allennlp_light/modules/attention/attention.py
allennlp_light/modules/attention/bilinear_attention.py
allennlp_light/modules/attention/cosine_attention.py
allennlp_light/modules/attention/dot_product_attention.py
allennlp_light/modules/attention/linear_attention.py
allennlp_light/modules/attention/scaled_dot_product_attention.py
allennlp_light/modules/conditional_random_field/__init__.py
allennlp_light/modules/conditional_random_field/conditional_random_field.py
allennlp_light/modules/conditional_random_field/conditional_random_field_wemission.py
allennlp_light/modules/conditional_random_field/conditional_random_field_wlannoy.py
allennlp_light/modules/conditional_random_field/conditional_random_field_wtrans.py
allennlp_light/modules/matrix_attention/__init__.py
allennlp_light/modules/matrix_attention/bilinear_matrix_attention.py
allennlp_light/modules/matrix_attention/cosine_matrix_attention.py
allennlp_light/modules/matrix_attention/dot_product_matrix_attention.py
allennlp_light-1.0.0.dist-info/LICENSE
allennlp_light-1.0.0.dist-info/METADATA
allennlp_light-1.0.0.dist-info/WHEEL
allennlp_light-1.0.0.dist-info/top_level.txt
allennlp_light-1.0.0.dist-info/RECORD
